cache_fastapi/__init__.py
cache_fastapi/cacheMiddleware.py
cache_fastapi/utils.py
cache_fastapi/wrappers.py
cache_fastapi/Backends/base_backend.py
cache_fastapi/Backends/memory_backend.py
cache_fastapi/Backends/redis_backend.py
cache_fastapi-0.0.6.dist-info/LICENSE
cache_fastapi-0.0.6.dist-info/METADATA
cache_fastapi-0.0.6.dist-info/WHEEL
cache_fastapi-0.0.6.dist-info/top_level.txt
cache_fastapi-0.0.6.dist-info/RECORD
